yc_django_logging/__init__.py
yc_django_logging/admin.py
yc_django_logging/apps.py
yc_django_logging/middleware.py
yc_django_logging/models.py
yc_django_logging/serializers.py
yc_django_logging/settings.py
yc_django_logging/tests.py
yc_django_logging/urls.py
yc_django_logging/utils.py
yc_django_logging/views.py
yc_django_logging/api/__init__.py
yc_django_logging/api/login_log.py
yc_django_logging/api/operation_log.py
yc_django_logging/migrations/0001_initial.py
yc_django_logging/migrations/__init__.py
yc_django_logging-0.0.7.dist-info/LICENSE
yc_django_logging-0.0.7.dist-info/METADATA
yc_django_logging-0.0.7.dist-info/WHEEL
yc_django_logging-0.0.7.dist-info/top_level.txt
yc_django_logging-0.0.7.dist-info/RECORD
