Metadata-Version: 2.1
Name: yc_django_logging
Version: 0.0.7
Summary: Django日志记录工具开发
Author: LiuFei
Author-email: liufei-love@foxmail.com
License: MIT
Classifier: License :: OSI Approved :: MIT License
Classifier: Programming Language :: Python :: 3.12
License-File: LICENSE
Requires-Dist: yc-django-utils >=0.0.3
Requires-Dist: django-simple-history >=3.7.0
